hello.cpython-38-x86_64-linux-gnu.so
tests.cpython-38-x86_64-linux-gnu.so
util.cpython-38-x86_64-linux-gnu.so
bootstrap/__init__.cpython-38-x86_64-linux-gnu.so
bootstrap/app.cpython-38-x86_64-linux-gnu.so
bootstrap/bootstrap.cpython-38-x86_64-linux-gnu.so
bootstrap/exceptions.cpython-38-x86_64-linux-gnu.so
bootstrap/util.cpython-38-x86_64-linux-gnu.so
bootstrap/crypto/rsa.cpython-38-x86_64-linux-gnu.so
bootstrap/installer/orka_installer.cpython-38-x86_64-linux-gnu.so
bootstrap/installer/smartpii/server_license_manager.cpython-38-x86_64-linux-gnu.so
bootstrap/installer/smartpii/smartpii_installer.cpython-38-x86_64-linux-gnu.so
tests/__init__.cpython-38-x86_64-linux-gnu.so
tests/docker_test.cpython-38-x86_64-linux-gnu.so
tests/scale_test.cpython-38-x86_64-linux-gnu.so
tests/test.cpython-38-x86_64-linux-gnu.so
tests/test_install.cpython-38-x86_64-linux-gnu.so
tests/test_install_docker.cpython-38-x86_64-linux-gnu.so
tests/test_keyring.cpython-38-x86_64-linux-gnu.so
tests/test_sysctl.cpython-38-x86_64-linux-gnu.so
smartpii_installer-1.1.79.dist-info/METADATA
smartpii_installer-1.1.79.dist-info/WHEEL
smartpii_installer-1.1.79.dist-info/entry_points.txt
smartpii_installer-1.1.79.dist-info/top_level.txt
smartpii_installer-1.1.79.dist-info/RECORD
