Metadata-Version: 2.1
Name: smartpii-installer
Version: 1.1.79
Summary: SmartPii installer
Home-page: http://www.orkunteknoloji.com.tr
Author: Sedat Kurtoglu
Author-email: sedatkurtoglu@gmail.com
License: UNKNOWN
Platform: UNKNOWN
Requires-Python: >=2.6, !=3.0.*, !=3.1.*, !=3.2.*
Requires-Dist: colorama
Requires-Dist: docker
